{"title":"IPH 312 - Child in the manger","verses":[{"lines":["Child in the manger,"," Infant of Mary;","outcast and stranger"," Lord of all!","\f Child who inherits","all our transgressions,"," all our demerits"," on Him fall."]},{"lines":["\fOnce the most holy","Child of salvation"," gentle and lowly"," lived below;","\fnow, as our glorious"," mighty Redeemer,"," see Him victorious"," o’er each foe."]},{"lines":["\fProphets foretold Him,"," Infant of wonder;"," angels behold Him"," on His throne;","\f worthy our Saviour"," of all their praises;"," happy for ever"," are His own."]}],"chorus":"","CCLI":"Mary Macdonald, 1789-1872\n translated Lachlan Macbean, 1853-1931 CCLI 128675"}